warc2zim/__about__.py
warc2zim/__init__.py
warc2zim/constants.py
warc2zim/converter.py
warc2zim/icon_finder.py
warc2zim/items.py
warc2zim/language.py
warc2zim/main.py
warc2zim/rewriting.py
warc2zim/utils.py
warc2zim/cdxj_indexer/__init__.py
warc2zim/cdxj_indexer/bufferiter.py
warc2zim/cdxj_indexer/main.py
warc2zim/cdxj_indexer/postquery.py
warc2zim/templates/head_insert.html
warc2zim-2.3.0.dist-info/METADATA
warc2zim-2.3.0.dist-info/WHEEL
warc2zim-2.3.0.dist-info/entry_points.txt
warc2zim-2.3.0.dist-info/licenses/LICENSE
warc2zim-2.3.0.dist-info/RECORD
