Metadata-Version: 2.4
Name: warc2zim
Version: 2.3.0
Summary: Convert WARC to ZIM
Project-URL: Donate, https://www.kiwix.org/en/support-us/
Project-URL: Homepage, https://github.com/openzim/warc2zim
Author-email: openZIM <dev@openzim.org>, Webrecorder Software <info@webrecorder.net>
License: GPL-3.0-or-later
License-File: LICENSE
Keywords: offline,openzim,warc,zim
Classifier: License :: OSI Approved :: GNU General Public License v3 or later (GPLv3+)
Classifier: Programming Language :: Python :: 3
Classifier: Programming Language :: Python :: 3.14
Requires-Python: <3.15,>=3.14
Requires-Dist: beautifulsoup4==4.14.3
Requires-Dist: brotlipy==0.7.0
Requires-Dist: jinja2==3.1.6
Requires-Dist: lxml==6.0.2
Requires-Dist: multipart==1.3.0
Requires-Dist: python-dateutil==2.9.0.post0
Requires-Dist: requests==2.32.5
Requires-Dist: tinycss2==1.5.1
Requires-Dist: warcio==1.7.5
Requires-Dist: zimscraperlib==5.3.0
Provides-Extra: check
Requires-Dist: pyright==1.1.394; extra == 'check'
Provides-Extra: dev
Requires-Dist: black==25.1.0; extra == 'dev'
Requires-Dist: coverage==7.6.12; extra == 'dev'
Requires-Dist: debugpy==1.8.12; extra == 'dev'
Requires-Dist: invoke==2.2.0; extra == 'dev'
Requires-Dist: pre-commit==4.1.0; extra == 'dev'
Requires-Dist: pyright==1.1.394; extra == 'dev'
Requires-Dist: pytest==8.3.4; extra == 'dev'
Requires-Dist: ruff==0.9.6; extra == 'dev'
Provides-Extra: lint
Requires-Dist: black==25.1.0; extra == 'lint'
Requires-Dist: ruff==0.9.6; extra == 'lint'
Provides-Extra: scripts
Requires-Dist: invoke==2.2.0; extra == 'scripts'
Provides-Extra: test
Requires-Dist: coverage==7.6.12; extra == 'test'
Requires-Dist: pytest==8.3.4; extra == 'test'
